antokel_cloud/__init__.py
antokel_cloud/aws/__init__.py
antokel_cloud/aws/ec2/__init__.py
antokel_cloud/aws/ec2/instance.py
antokel_cloud/aws/ec2/volume.py
antokel_cloud/aws/ec2/user_data/__init__.py
antokel_cloud/aws/ec2/user_data/base.py
antokel_cloud/aws/ec2/user_data/container_fleet.py
antokel_cloud/aws/s3/__init__.py
antokel_cloud/aws/s3/text.py
antokel_cloud-0.0.7.dist-info/METADATA
antokel_cloud-0.0.7.dist-info/WHEEL
antokel_cloud-0.0.7.dist-info/licenses/LICENSE
antokel_cloud-0.0.7.dist-info/RECORD
