Metadata-Version: 2.4
Name: antokel-cloud
Version: 0.0.7
Summary: Cloud SDK for Antokel engineers
Project-URL: Homepage, https://github.com/zPy52/antokel-cloud
Project-URL: Repository, https://github.com/zPy52/antokel-cloud
Project-URL: Issues, https://github.com/zPy52/antokel-cloud/issues
Author-email: Antonio Peña Peña <toni@antokel.com>
License:                                  Apache License
License-File: LICENSE
Classifier: Development Status :: 3 - Alpha
Classifier: Intended Audience :: Developers
Classifier: License :: OSI Approved :: Apache Software License
Classifier: Programming Language :: Python :: 3
Classifier: Programming Language :: Python :: 3.8
Classifier: Programming Language :: Python :: 3.9
Classifier: Programming Language :: Python :: 3.10
Classifier: Programming Language :: Python :: 3.11
Classifier: Programming Language :: Python :: 3.12
Requires-Python: >=3.8
Requires-Dist: boto3
